autohex/__init__.py
autohex-0.1.1.dist-info/licenses/LICENSE.txt
autohex-0.1.1.dist-info/METADATA
autohex-0.1.1.dist-info/WHEEL
autohex-0.1.1.dist-info/top_level.txt
autohex-0.1.1.dist-info/RECORD
