Metadata-Version: 2.4
Name: autohex
Version: 0.1.1
Summary: Generate unique and vibrant hex color codes from text.
Author-email: Jeonghwan Park <reniya@kaist.ac.kr>
Keywords: color,hex,generator,hash,hsl
Classifier: Development Status :: 3 - Alpha
Classifier: Intended Audience :: Developers
Classifier: License :: OSI Approved :: MIT License
Classifier: Programming Language :: Python :: 3
Classifier: Programming Language :: Python :: 3.8
Classifier: Programming Language :: Python :: 3.9
Classifier: Programming Language :: Python :: 3.10
Classifier: Programming Language :: Python :: 3.11
Classifier: Topic :: Software Development :: Libraries :: Python Modules
Classifier: Topic :: Multimedia :: Graphics
Requires-Python: >=3.8
License-File: LICENSE.txt
Dynamic: license-file
